.gitignore
CODE_OF_CONDUCT.md
CONTRIBUTING.md
LICENSE
README.md
discord_gift_checker.py
integrated_tool.py
pyproject.toml
requirements.txt
run_integrated.bat
setup.cfg
setup.py
data/proxies.txt
nitro_toolkit-2.1.3.dist-info/licenses/LICENSE
nitro_toolkit.egg-info/PKG-INFO
nitro_toolkit.egg-info/SOURCES.txt
nitro_toolkit.egg-info/dependency_links.txt
nitro_toolkit.egg-info/entry_points.txt
nitro_toolkit.egg-info/requires.txt
nitro_toolkit.egg-info/top_level.txt
nitro_toolkit-2.1.3.dist-info/METADATA
nitro_toolkit-2.1.3.dist-info/WHEEL
nitro_toolkit-2.1.3.dist-info/entry_points.txt
nitro_toolkit-2.1.3.dist-info/top_level.txt
nitro_toolkit-2.1.3.dist-info/RECORD
