Metadata-Version: 2.4
Name: nitro-toolkit
Version: 2.1.3
Summary: Discord Nitro gift code generator and checker toolkit
Home-page: https://github.com/HenryLok0/nitro-toolkit
Author: HenryLok0
Author-email: HenryLok0 <your.email@example.com>
License: MIT
Project-URL: Homepage, https://github.com/HenryLok0/discord
Project-URL: Bug Reports, https://github.com/HenryLok0/discord/issues
Project-URL: Source, https://github.com/HenryLok0/discord
Project-URL: Documentation, https://github.com/HenryLok0/discord/blob/main/README.md
Keywords: discord,nitro,generator,checker,gift,codes,api
Classifier: Development Status :: 4 - Beta
Classifier: Intended Audience :: Developers
Classifier: Topic :: Software Development :: Libraries :: Python Modules
Classifier: License :: OSI Approved :: MIT License
Classifier: Programming Language :: Python :: 3
Classifier: Programming Language :: Python :: 3.6
Classifier: Programming Language :: Python :: 3.7
Classifier: Programming Language :: Python :: 3.8
Classifier: Programming Language :: Python :: 3.9
Classifier: Programming Language :: Python :: 3.10
Classifier: Programming Language :: Python :: 3.11
Classifier: Operating System :: OS Independent
Requires-Python: >=3.6
License-File: LICENSE
Requires-Dist: requests>=2.25.0
Requires-Dist: colorama>=0.4.0
Requires-Dist: inquirer
Dynamic: author
Dynamic: home-page
Dynamic: license-file
Dynamic: requires-python
